README.md
setup.py
pomice/__init__.py
pomice/enums.py
pomice/events.py
pomice/exceptions.py
pomice/filters.py
pomice/objects.py
pomice/player.py
pomice/pool.py
pomice/utils.py
pomice/spotify/__init__.py
pomice/spotify/album.py
pomice/spotify/client.py
pomice/spotify/exceptions.py
pomice/spotify/playlist.py
pomice/spotify/track.py
pomicenextcord.egg-info/PKG-INFO
pomicenextcord.egg-info/SOURCES.txt
pomicenextcord.egg-info/dependency_links.txt
pomicenextcord.egg-info/top_level.txt